marshmallow_jsonschema_3/__init__.py
marshmallow_jsonschema_3/base.py
marshmallow_jsonschema_3/exceptions.py
marshmallow_jsonschema_3/validation.py
marshmallow_jsonschema_3-1.0.9.dist-info/LICENSE
marshmallow_jsonschema_3-1.0.9.dist-info/METADATA
marshmallow_jsonschema_3-1.0.9.dist-info/WHEEL
marshmallow_jsonschema_3-1.0.9.dist-info/top_level.txt
marshmallow_jsonschema_3-1.0.9.dist-info/RECORD
