Metadata-Version: 2.1
Name: marshmallow-jsonschema-3
Version: 1.0.9
Summary: Marshmallow schema to OpenAPI 3.0.x-3.1 spec. Fork of marshmallow-jsonschema by Stephen J. Fuhry.
Author: 10Speed
Author-email: info@10speed.cloud
License: MIT License
Keywords: marshmallow-jsonschema marshmallow schema serialization jsonschema validation openapi openapi3.1 openapi3.0
Platform: UNKNOWN
Classifier: Intended Audience :: Developers
Classifier: License :: OSI Approved :: MIT License
Classifier: Natural Language :: English
Classifier: Programming Language :: Python :: 3
Classifier: Programming Language :: Python :: 3.8
Classifier: Programming Language :: Python :: 3.9
Classifier: Programming Language :: Python :: 3.10
Requires-Python: >=3.8
License-File: LICENSE
Requires-Dist: marshmallow (>=3.15)
Provides-Extra: enum
Requires-Dist: marshmallow-enum ; extra == 'enum'
Provides-Extra: union
Requires-Dist: marshmallow-union ; extra == 'union'
